{"examples_composite-action.md":"uIgtZBIT","examples_javascript-action.md":"C8iHG1iQ","examples_matrix-build.md":"DNhuZrMP","examples_simple-ci.md":"BiDglJxr","guide_configuration.md":"BvQI4Ry2","guide_getting-started.md":"BxYSOox_","guide_installation.md":"3y54KXyH","guide_migration.md":"jJ5leUVQ","guide_why.md":"BMB18d_7","guide_writing-workflows.md":"CRxF9txx","index.md":"BIRbS0l2","ko_examples_composite-action.md":"CjZvQ34q","ko_examples_javascript-action.md":"C4Nqba2K","ko_examples_matrix-build.md":"14hUtH3P","ko_examples_simple-ci.md":"D2mSVMMz","ko_guide_configuration.md":"TUGKf1aG","ko_guide_getting-started.md":"Wh3ECAig","ko_guide_installation.md":"CIrgUbVc","ko_guide_migration.md":"DWWibU4z","ko_guide_why.md":"CPhjDqoT","ko_guide_writing-workflows.md":"C-G7ti0-","ko_index.md":"Jo7dPZQR","ko_reference_actions.md":"D4x4l4Hp","ko_reference_api.md":"RSimNM13","ko_reference_cli.md":"Cy85SlES","reference_actions.md":"DVWcIOCS","reference_api.md":"jGYHJzJd","reference_cli.md":"CvGRLUlR"}
